boltworks/__init__.py
boltworks/boltworks.py
boltworks/callbacks/action_callbacks.py
boltworks/callbacks/thread_callbacks.py
boltworks/cli/__init__.py
boltworks/cli/argparse_decorator.py
boltworks/gui/__init__.py
boltworks/gui/expandpointer.py
boltworks/gui/treenodeui.py
boltworks/helper/__init__.py
boltworks/helper/kvstore.py
boltworks/helper/serializers.py
boltworks/helper/slack_utils.py
boltworks-0.1.0.dist-info/LICENSE
boltworks-0.1.0.dist-info/METADATA
boltworks-0.1.0.dist-info/WHEEL
boltworks-0.1.0.dist-info/RECORD
