Metadata-Version: 2.1
Name: boltworks
Version: 0.1.0
Summary: A collection of decorators and functionns for Slack's bolt library to help you make a better slackbot.
Home-page: https://github.com/ysaxon/boltworks
License: MIT
Author: Yaakov Saxon
Author-email: ysaxon@gmail.com
Requires-Python: >=3.8.0,<4.0
Classifier: Development Status :: 2 - Pre-Alpha
Classifier: Intended Audience :: Developers
Classifier: License :: OSI Approved :: MIT License
Classifier: Natural Language :: English
Classifier: Programming Language :: Python :: 3
Classifier: Programming Language :: Python :: 3.8
Classifier: Programming Language :: Python :: 3.9
Classifier: Programming Language :: Python :: 3.10
Classifier: Programming Language :: Python :: 3.11
Classifier: Programming Language :: Python :: 3
Classifier: Programming Language :: Python :: 3.10
Classifier: Programming Language :: Python :: 3.8
Classifier: Programming Language :: Python :: 3.9
Provides-Extra: dev
Provides-Extra: doc
Provides-Extra: test
Requires-Dist: black (>=22.3.0,<23.0.0) ; extra == "test"
Requires-Dist: dill (>=0.3.6,<0.4.0)
Requires-Dist: diskcache (>=5.4.0,<6.0.0)
Requires-Dist: expiringdict (>=1.2.2,<2.0.0)
Requires-Dist: flake8 (==4.0.1) ; extra == "test"
Requires-Dist: flake8-docstrings (>=1.6.0,<2.0.0) ; extra == "test"
Requires-Dist: isort (==5.10.1) ; extra == "test"
Requires-Dist: itsdangerous (>=2.1.2,<3.0.0)
Requires-Dist: jinja2 (==3.0.3)
Requires-Dist: livereload (>=2.6.3,<3.0.0)
Requires-Dist: mkdocs (>=1.2.4,<2.0.0) ; extra == "doc"
Requires-Dist: mkdocs-autorefs (>=0.3.1,<0.4.0) ; extra == "doc"
Requires-Dist: mkdocs-include-markdown-plugin (>=3.2.3,<4.0.0) ; extra == "doc"
Requires-Dist: mkdocs-material (>=8.1.11,<9.0.0) ; extra == "doc"
Requires-Dist: mkdocs-material-extensions (>=1.0.3,<2.0.0)
Requires-Dist: mkdocstrings (>=0.18.0,<0.19.0) ; extra == "doc"
Requires-Dist: more-itertools (>=9.1.0,<10.0.0)
Requires-Dist: pip (>=22.0.3,<23.0.0) ; extra == "dev"
Requires-Dist: pre-commit (>=2.17.0,<3.0.0) ; extra == "dev"
Requires-Dist: pyreadline (>=2.1,<3.0)
Requires-Dist: pytest (>=7.0.1,<8.0.0) ; extra == "test"
Requires-Dist: pytest-cov (>=3.0.0,<4.0.0) ; extra == "test"
Requires-Dist: pyyaml (>=6.0,<7.0) ; extra == "test"
Requires-Dist: slack-bolt (>=1.14.0,<2.0.0)
Requires-Dist: slack-sdk (>=3.20.0,<4.0.0)
Requires-Dist: toml (>=0.10.2,<0.11.0) ; extra == "dev"
Requires-Dist: tox (>=3.24.5,<4.0.0) ; extra == "dev"
Requires-Dist: twine (>=3.8.0,<4.0.0) ; extra == "dev"
Requires-Dist: virtualenv (>=20.13.1,<21.0.0) ; extra == "dev"
